search_impact_factor/2022_JCR_IF.csv
search_impact_factor/2023_JCR_IF.csv
search_impact_factor/__init__.py
search_impact_factor/search_impact_factor.py
search_impact_factor-0.0.11.dist-info/LICENSE
search_impact_factor-0.0.11.dist-info/METADATA
search_impact_factor-0.0.11.dist-info/WHEEL
search_impact_factor-0.0.11.dist-info/top_level.txt
search_impact_factor-0.0.11.dist-info/RECORD
