Metadata-Version: 2.1
Name: search-impact-factor
Version: 0.0.11
Summary: A package to query the impact factor database
Home-page: https://github.com/Brritany/search_impact_factor
Author: hyz
Author-email: m946111005@tmu.edu.tw
License: UNKNOWN
Project-URL: Tracker, https://github.com/Brritany/search_impact_factor/issues
Keywords: python,impact factor,IF
Platform: UNKNOWN
Classifier: Development Status :: 5 - Production/Stable
Classifier: Intended Audience :: Science/Research
Classifier: License :: OSI Approved :: MIT License
Classifier: Natural Language :: Chinese (Traditional)
Classifier: Topic :: Software Development :: Libraries
Classifier: Programming Language :: Python :: 3.6
Classifier: Programming Language :: Python :: 3.7
Classifier: Programming Language :: Python :: 3.8
Classifier: Programming Language :: Python :: 3.9
License-File: LICENSE
Requires-Dist: pandas
